[
  {
    "id": "d8441aa7-52b9-4aa3-8890-2200b019fdf2",
    "userId": "6632ce92-1807-4b0f-b1e5-53184ebaf225",
    "object": "lampioni possibilmente",
    "nomeUtente": "nameUser subnameUser",
    "content": "richiesta di lampioni lungo la via",
    "createdAt": "2025-08-03T14:02:06.332Z"
  },
  {
    "id": "c9fa437c-be68-4408-83b7-63ff15d623ab",
    "userId": "ad906063-faf9-471d-8f45-7a7716365a47",
    "object": "spazzatura",
    "nomeUtente": "giovanni impastato",
    "content": "la spazzatura deve essere cacciata solo la sera! altrimenti puzza",
    "createdAt": "2025-08-03T14:03:25.887Z"
  },
  {
    "id": "9b47089d-7545-434a-815d-429df2f062a8",
    "userId": "53b37688-0fc8-428a-aa75-df4e6cc3adcd",
    "object": "Richiesta di aggiungere le luci natalizie",
    "nomeUtente": "gabriella conte",
    "content": "questo natale vorrei proporre di stanziare dei fondi per creare uno spettacolo di natale uguale per tutti!",
    "createdAt": "2025-08-03T14:04:13.442Z"
  },
  {
    "id": "3c7eabd2-8caf-494b-a2d0-eb21320687f8",
    "userId": "53b37688-0fc8-428a-aa75-df4e6cc3adcd",
    "object": "Per Admin",
    "nomeUtente": "gabriella conte",
    "content": "Ci tenevo a precisare che l'admin Marco è tutto MINKIA ma io lo amo da morire",
    "createdAt": "2025-08-03T15:33:24.368Z"
  }
]